[
    [
      { "color": "RED" },
      { "color": "BLANK" },
      { "color": "BLUE" },
      { "color": "BLANK" },
      { "color": "YELLOW" }
    ],
    [
      { "value": 4 },
      { "color": "PURPLE" },
      { "value": 3 },
      { "color": "GREEN" },
      { "value": 2 }
    ],
    [
      { "color": "BLANK" },
      { "value": 1 },
      { "color": "BLANK" },
      { "value": 5 },
      { "color": "BLANK" }
    ],
    [
      { "color": "BLANK" },
      { "color": "BLANK" },
      { "value": 6 },
      { "color": "BLANK" },
      { "color": "BLANK" }
    ]
]